{
  "lastUpdated": "2025-05-09T07:10:56.456Z",
  "dataPoints": [
    {
      "timestamp": "2025-05-09T07:10:56.452Z",
      "postCount": 20,
      "totalVotes": 930,
      "topPosts": [
        {
          "name": "HyperArc",
          "votes": 65,
          "url": "https://www.producthunt.com/posts/hyperarc?utm_campaign=producthunt-api&utm_medium=api-v2&utm_source=Application%3A+snapshot+%28ID%3A+184942%29"
        },
        {
          "name": "Antispace",
          "votes": 56,
          "url": "https://www.producthunt.com/posts/antispace-3?utm_campaign=producthunt-api&utm_medium=api-v2&utm_source=Application%3A+snapshot+%28ID%3A+184942%29"
        },
        {
          "name": "Qagent",
          "votes": 57,
          "url": "https://www.producthunt.com/posts/qagent?utm_campaign=producthunt-api&utm_medium=api-v2&utm_source=Application%3A+snapshot+%28ID%3A+184942%29"
        },
        {
          "name": "Pipedream MCP",
          "votes": 56,
          "url": "https://www.producthunt.com/posts/pipedream-mcp?utm_campaign=producthunt-api&utm_medium=api-v2&utm_source=Application%3A+snapshot+%28ID%3A+184942%29"
        },
        {
          "name": "pfp.fm",
          "votes": 55,
          "url": "https://www.producthunt.com/posts/pfp-fm?utm_campaign=producthunt-api&utm_medium=api-v2&utm_source=Application%3A+snapshot+%28ID%3A+184942%29"
        }
      ]
    }
  ]
}