{
  "lastUpdated": "2025-05-24T11:19:13.453Z",
  "dataPoints": [
    {
      "timestamp": "2025-05-24T11:19:13.449Z",
      "postCount": 20,
      "totalVotes": 937,
      "topPosts": [
        {
          "name": "Uplyt.io",
          "votes": 155,
          "url": "https://www.producthunt.com/posts/uplyt-io?utm_campaign=producthunt-api&utm_medium=api-v2&utm_source=Application%3A+snapshot+%28ID%3A+184942%29"
        },
        {
          "name": "Shotomatic",
          "votes": 136,
          "url": "https://www.producthunt.com/posts/shotomatic?utm_campaign=producthunt-api&utm_medium=api-v2&utm_source=Application%3A+snapshot+%28ID%3A+184942%29"
        },
        {
          "name": "Psyche",
          "votes": 126,
          "url": "https://www.producthunt.com/posts/psyche?utm_campaign=producthunt-api&utm_medium=api-v2&utm_source=Application%3A+snapshot+%28ID%3A+184942%29"
        },
        {
          "name": "Magentic-UI",
          "votes": 121,
          "url": "https://www.producthunt.com/posts/magentic-ui?utm_campaign=producthunt-api&utm_medium=api-v2&utm_source=Application%3A+snapshot+%28ID%3A+184942%29"
        },
        {
          "name": "vibecheck",
          "votes": 110,
          "url": "https://www.producthunt.com/posts/vibecheck?utm_campaign=producthunt-api&utm_medium=api-v2&utm_source=Application%3A+snapshot+%28ID%3A+184942%29"
        }
      ]
    }
  ]
}