{
  "lastUpdated": "2025-06-09T05:52:06.062Z",
  "dataPoints": [
    {
      "timestamp": "2025-06-09T05:52:06.059Z",
      "postCount": 20,
      "totalVotes": 2141,
      "topPosts": [
        {
          "name": "SocLeads 2.0",
          "votes": 570,
          "url": "https://www.producthunt.com/posts/socleads-2-0?utm_campaign=producthunt-api&utm_medium=api-v2&utm_source=Application%3A+snapshot+%28ID%3A+184942%29"
        },
        {
          "name": "VidAU ",
          "votes": 478,
          "url": "https://www.producthunt.com/posts/vidau-2?utm_campaign=producthunt-api&utm_medium=api-v2&utm_source=Application%3A+snapshot+%28ID%3A+184942%29"
        },
        {
          "name": "(Not Boring) Camera",
          "votes": 311,
          "url": "https://www.producthunt.com/posts/not-boring-camera?utm_campaign=producthunt-api&utm_medium=api-v2&utm_source=Application%3A+snapshot+%28ID%3A+184942%29"
        },
        {
          "name": "Zeno",
          "votes": 234,
          "url": "https://www.producthunt.com/posts/zeno-3?utm_campaign=producthunt-api&utm_medium=api-v2&utm_source=Application%3A+snapshot+%28ID%3A+184942%29"
        },
        {
          "name": "BountyHub ",
          "votes": 213,
          "url": "https://www.producthunt.com/posts/bountyhub-2?utm_campaign=producthunt-api&utm_medium=api-v2&utm_source=Application%3A+snapshot+%28ID%3A+184942%29"
        }
      ]
    }
  ]
}