{
  "lastUpdated": "2025-04-29T07:36:32.589Z",
  "dataPoints": [
    {
      "timestamp": "2025-04-29T07:36:32.586Z",
      "postCount": 20,
      "totalVotes": 1273,
      "topPosts": [
        {
          "name": "Whoa!",
          "votes": 77,
          "url": "https://www.producthunt.com/posts/whoa?utm_campaign=producthunt-api&utm_medium=api-v2&utm_source=Application%3A+snapshot+%28ID%3A+184942%29"
        },
        {
          "name": "Bruno ",
          "votes": 79,
          "url": "https://www.producthunt.com/posts/bruno-6?utm_campaign=producthunt-api&utm_medium=api-v2&utm_source=Application%3A+snapshot+%28ID%3A+184942%29"
        },
        {
          "name": "Transkriptor 2.0",
          "votes": 68,
          "url": "https://www.producthunt.com/posts/transkriptor-2-0?utm_campaign=producthunt-api&utm_medium=api-v2&utm_source=Application%3A+snapshot+%28ID%3A+184942%29"
        },
        {
          "name": "Daytona ",
          "votes": 67,
          "url": "https://www.producthunt.com/posts/daytona-2?utm_campaign=producthunt-api&utm_medium=api-v2&utm_source=Application%3A+snapshot+%28ID%3A+184942%29"
        },
        {
          "name": "TurboSQL",
          "votes": 64,
          "url": "https://www.producthunt.com/posts/turbosql?utm_campaign=producthunt-api&utm_medium=api-v2&utm_source=Application%3A+snapshot+%28ID%3A+184942%29"
        }
      ]
    }
  ]
}