{
  "lastUpdated": "2025-05-24T20:34:48.328Z",
  "dataPoints": [
    {
      "timestamp": "2025-05-24T20:34:48.325Z",
      "postCount": 20,
      "totalVotes": 1755,
      "topPosts": [
        {
          "name": "Uplyt.io",
          "votes": 299,
          "url": "https://www.producthunt.com/posts/uplyt-io?utm_campaign=producthunt-api&utm_medium=api-v2&utm_source=Application%3A+snapshot+%28ID%3A+184942%29"
        },
        {
          "name": "Shotomatic",
          "votes": 214,
          "url": "https://www.producthunt.com/posts/shotomatic?utm_campaign=producthunt-api&utm_medium=api-v2&utm_source=Application%3A+snapshot+%28ID%3A+184942%29"
        },
        {
          "name": "Psyche",
          "votes": 202,
          "url": "https://www.producthunt.com/posts/psyche?utm_campaign=producthunt-api&utm_medium=api-v2&utm_source=Application%3A+snapshot+%28ID%3A+184942%29"
        },
        {
          "name": "Magentic-UI",
          "votes": 178,
          "url": "https://www.producthunt.com/posts/magentic-ui?utm_campaign=producthunt-api&utm_medium=api-v2&utm_source=Application%3A+snapshot+%28ID%3A+184942%29"
        },
        {
          "name": "vibecheck",
          "votes": 162,
          "url": "https://www.producthunt.com/posts/vibecheck?utm_campaign=producthunt-api&utm_medium=api-v2&utm_source=Application%3A+snapshot+%28ID%3A+184942%29"
        }
      ]
    }
  ]
}