{
  "lastUpdated": "2025-05-10T20:31:39.287Z",
  "dataPoints": [
    {
      "timestamp": "2025-05-10T20:31:39.283Z",
      "postCount": 20,
      "totalVotes": 2082,
      "topPosts": [
        {
          "name": "SeeMuseums",
          "votes": 335,
          "url": "https://www.producthunt.com/posts/seemuseums?utm_campaign=producthunt-api&utm_medium=api-v2&utm_source=Application%3A+snapshot+%28ID%3A+184942%29"
        },
        {
          "name": "Rubber Duck Armada",
          "votes": 231,
          "url": "https://www.producthunt.com/posts/rubber-duck-armada?utm_campaign=producthunt-api&utm_medium=api-v2&utm_source=Application%3A+snapshot+%28ID%3A+184942%29"
        },
        {
          "name": "Aladin",
          "votes": 215,
          "url": "https://www.producthunt.com/posts/aladin?utm_campaign=producthunt-api&utm_medium=api-v2&utm_source=Application%3A+snapshot+%28ID%3A+184942%29"
        },
        {
          "name": "Photo AI 4",
          "votes": 180,
          "url": "https://www.producthunt.com/posts/photo-ai-4?utm_campaign=producthunt-api&utm_medium=api-v2&utm_source=Application%3A+snapshot+%28ID%3A+184942%29"
        },
        {
          "name": "Aurascope",
          "votes": 163,
          "url": "https://www.producthunt.com/posts/aurascope?utm_campaign=producthunt-api&utm_medium=api-v2&utm_source=Application%3A+snapshot+%28ID%3A+184942%29"
        }
      ]
    }
  ]
}