{
  "lastUpdated": "2025-05-21T14:54:18.465Z",
  "dataPoints": [
    {
      "timestamp": "2025-05-21T14:54:18.461Z",
      "postCount": 20,
      "totalVotes": 2804,
      "topPosts": [
        {
          "name": "Algebras AI",
          "votes": 427,
          "url": "https://www.producthunt.com/posts/algebras-ai?utm_campaign=producthunt-api&utm_medium=api-v2&utm_source=Application%3A+snapshot+%28ID%3A+184942%29"
        },
        {
          "name": "Super",
          "votes": 229,
          "url": "https://www.producthunt.com/posts/super-7dae3a55-088b-4ef3-bfae-921c73bbe94e?utm_campaign=producthunt-api&utm_medium=api-v2&utm_source=Application%3A+snapshot+%28ID%3A+184942%29"
        },
        {
          "name": "Google Flow",
          "votes": 173,
          "url": "https://www.producthunt.com/posts/google-flow?utm_campaign=producthunt-api&utm_medium=api-v2&utm_source=Application%3A+snapshot+%28ID%3A+184942%29"
        },
        {
          "name": "Head AI (Alpha)",
          "votes": 151,
          "url": "https://www.producthunt.com/posts/head-ai-alpha?utm_campaign=producthunt-api&utm_medium=api-v2&utm_source=Application%3A+snapshot+%28ID%3A+184942%29"
        },
        {
          "name": "Langfuse Custom Dashboards",
          "votes": 137,
          "url": "https://www.producthunt.com/posts/langfuse-custom-dashboards?utm_campaign=producthunt-api&utm_medium=api-v2&utm_source=Application%3A+snapshot+%28ID%3A+184942%29"
        }
      ]
    }
  ]
}