{
  "lastUpdated": "2025-05-10T14:31:57.568Z",
  "dataPoints": [
    {
      "timestamp": "2025-05-10T14:31:57.564Z",
      "postCount": 20,
      "totalVotes": 1626,
      "topPosts": [
        {
          "name": "SeeMuseums",
          "votes": 230,
          "url": "https://www.producthunt.com/posts/seemuseums?utm_campaign=producthunt-api&utm_medium=api-v2&utm_source=Application%3A+snapshot+%28ID%3A+184942%29"
        },
        {
          "name": "Rubber Duck Armada",
          "votes": 172,
          "url": "https://www.producthunt.com/posts/rubber-duck-armada?utm_campaign=producthunt-api&utm_medium=api-v2&utm_source=Application%3A+snapshot+%28ID%3A+184942%29"
        },
        {
          "name": "Aladin",
          "votes": 164,
          "url": "https://www.producthunt.com/posts/aladin?utm_campaign=producthunt-api&utm_medium=api-v2&utm_source=Application%3A+snapshot+%28ID%3A+184942%29"
        },
        {
          "name": "Photo AI 4",
          "votes": 153,
          "url": "https://www.producthunt.com/posts/photo-ai-4?utm_campaign=producthunt-api&utm_medium=api-v2&utm_source=Application%3A+snapshot+%28ID%3A+184942%29"
        },
        {
          "name": "Aurascope",
          "votes": 136,
          "url": "https://www.producthunt.com/posts/aurascope?utm_campaign=producthunt-api&utm_medium=api-v2&utm_source=Application%3A+snapshot+%28ID%3A+184942%29"
        }
      ]
    }
  ]
}